odoo8_addon_sale_transport_multi_address-8.0.1.0.0-py2.7-nspkg.pth
odoo_addons/sale_transport_multi_address/__openerp__.py
odoo_addons/sale_transport_multi_address/__init__.py
odoo_addons/sale_transport_multi_address/README.rst
odoo_addons/sale_transport_multi_address/view/sale.xml
odoo_addons/sale_transport_multi_address/view/report_saleorder.xml
odoo_addons/sale_transport_multi_address/i18n/es.po
odoo_addons/sale_transport_multi_address/i18n/sale_transport_multi_address.pot
odoo_addons/sale_transport_multi_address/model/sale_order.py
odoo_addons/sale_transport_multi_address/model/__init__.py
odoo_addons/sale_transport_multi_address/test/test_report.yml
odoo_addons/sale_transport_multi_address/tests/test_consignee_sale_order.py
odoo_addons/sale_transport_multi_address/tests/__init__.py
odoo_addons/sale_transport_multi_address/demo/sale.xml
odoo_addons/sale_transport_multi_address/static/description/icon.png
odoo8_addon_sale_transport_multi_address-8.0.1.0.0.dist-info/top_level.txt
odoo8_addon_sale_transport_multi_address-8.0.1.0.0.dist-info/WHEEL
odoo8_addon_sale_transport_multi_address-8.0.1.0.0.dist-info/RECORD
odoo8_addon_sale_transport_multi_address-8.0.1.0.0.dist-info/metadata.json
odoo8_addon_sale_transport_multi_address-8.0.1.0.0.dist-info/DESCRIPTION.rst
odoo8_addon_sale_transport_multi_address-8.0.1.0.0.dist-info/METADATA
odoo8_addon_sale_transport_multi_address-8.0.1.0.0.dist-info/namespace_packages.txt
